days_until/__init__.py
days_until/__main__.py
days_until/__version__.py
days_until-0.0.1.dist-info/METADATA
days_until-0.0.1.dist-info/WHEEL
days_until-0.0.1.dist-info/entry_points.txt
days_until-0.0.1.dist-info/top_level.txt
days_until-0.0.1.dist-info/RECORD
