Metadata-Version: 2.1
Name: days-until
Version: 0.0.1
Summary: CLI to count down days until events.
Home-page: https://github.com/alichtman/days_until
Author: Aaron Lichtman
Author-email: aaronlichtman@gmail.com
License: MIT
Platform: UNKNOWN
Classifier: License :: OSI Approved :: MIT License
Classifier: Programming Language :: Python
Classifier: Programming Language :: Python :: 3
Classifier: Programming Language :: Python :: 3.6
Classifier: Programming Language :: Python :: Implementation :: CPython
Classifier: Programming Language :: Python :: Implementation :: PyPy
Requires-Python: >=3.6.0
Requires-Dist: click
Requires-Dist: colorama
Requires-Dist: pyyaml
